eyesonlineui/__init__.py
eyesonlineui/app.py
eyesonlineui/client_login.py
eyesonlineui/multitest.py
eyesonlineui/socketcontroller.py
eyesonlineui/testimport.py
eyesonlineui/utilities.py
eyesonlineui/templates/__init__.py
eyesonlineui/templates/build_details.py
eyesonlineui/templates/layout3.py
eyesonlineui/templates/res_rc.py
eyesonlineui/templates/ui_exptEntry.py
eyesonlineui/templates/ui_exptEntryHeader.py
eyesonlineui/templates/ui_joinDialog.py
eyesonlineui/templates/ui_layout3.py
eyesonlineui/templates/ui_loginDialog.py
eyesonlineui/themes/__init__.py
eyesonlineui/themes/amoled.qss
eyesonlineui/themes/aqua.qss
eyesonlineui/themes/material.qss
resources/99-eyes17-pip.rules
resources/__init__.py
resources/sispmctl.conf
eyesonline-1.0.16.dist-info/LICENSE
eyesonline-1.0.16.dist-info/METADATA
eyesonline-1.0.16.dist-info/WHEEL
eyesonline-1.0.16.dist-info/entry_points.txt
eyesonline-1.0.16.dist-info/top_level.txt
eyesonline-1.0.16.dist-info/RECORD
