Metadata-Version: 2.1
Name: eyesonline
Version: 1.0.16
Summary: Python package for Remote Access of Eyes17 and other hardware
Home-page: https://github.com/csparkresearch/expeyes17
Author: Jithin B.P
Author-email: jithinbp@gmail.com
License: UNKNOWN
Project-URL: Source, https://github.com/expeyes/expeyes-programs
Project-URL: Read The Docs, https://expeyes.in
Project-URL: Buy Hardware, https://csparkresearch.in/expeyes17
Keywords: expeyes17 data-acquisition remote-access virtual-lab lab-at-home oscilloscope waveform-generator sensors physics
Platform: UNKNOWN
Classifier: Development Status :: 5 - Production/Stable
Classifier: Intended Audience :: Education
Classifier: Programming Language :: Python :: 3
Classifier: License :: OSI Approved :: MIT License
Classifier: Operating System :: OS Independent
Requires-Python: >=3
Requires-Dist: pip
Requires-Dist: pyserial
Requires-Dist: numpy
Requires-Dist: scipy
Requires-Dist: PyQt5
Requires-Dist: pyqtwebengine
Requires-Dist: pyqtgraph
Requires-Dist: matplotlib
Requires-Dist: requests
Requires-Dist: flask
Requires-Dist: flask-socketio
